rewire/__init__.py
rewire/classproperty.py
rewire/config.py
rewire/context.py
rewire/dependencies.py
rewire/lifecycle.py
rewire/loader.py
rewire/log.py
rewire/plugins.py
rewire/py.typed
rewire/space.py
rewire/store.py
rewire-0.10.4.dist-info/LICENSE
rewire-0.10.4.dist-info/METADATA
rewire-0.10.4.dist-info/WHEEL
rewire-0.10.4.dist-info/top_level.txt
rewire-0.10.4.dist-info/RECORD
