Metadata-Version: 2.2
Name: rewire
Version: 0.10.4
Summary: A Streamlined Type-Based Dependency Injection Framework
Author-email: Ivan Vozhakov <gou177@bk.ru>
License: MIT License
Project-URL: Homepage, https://github.com/rewirepy/rewire
Keywords: dependency injection,configuration managment
Classifier: License :: OSI Approved :: MIT License
Classifier: Programming Language :: Python
Classifier: Programming Language :: Python :: 3
Requires-Python: >=3.12
License-File: LICENSE
Requires-Dist: pydantic>=2.0.0
Requires-Dist: anyio>=4.0.0
Requires-Dist: PyYAML>=6.0.1
Requires-Dist: loguru<=1.0.0
Provides-Extra: dev
Requires-Dist: black; extra == "dev"
Requires-Dist: pytest; extra == "dev"
Requires-Dist: trio; extra == "dev"
Requires-Dist: pytest-anyio; extra == "dev"
Requires-Dist: graphviz; extra == "dev"
